tuskar_ui-0.4.0.dist-info/METADATA
tuskar_ui-0.4.0.dist-info/WHEEL
tuskar_ui-0.4.0.dist-info/metadata.json
tuskar_ui-0.4.0.dist-info/RECORD
tuskar_ui-0.4.0.dist-info/top_level.txt
tuskar_ui-0.4.0.dist-info/DESCRIPTION.rst
tuskar_ui-0.4.0.dist-info/pbr.json
tuskar_ui/exceptions.py
tuskar_ui/__init__.py
tuskar_ui/cached_property.py
tuskar_ui/tables.py
tuskar_ui/handle_errors.py
tuskar_ui/forms.py
tuskar_ui/utils/__init__.py
tuskar_ui/utils/tests.py
tuskar_ui/utils/utils.py
tuskar_ui/utils/metering.py
tuskar_ui/test/settings.py
tuskar_ui/test/urls.py
tuskar_ui/test/formset_table_tests.py
tuskar_ui/test/selenium.py
tuskar_ui/test/test_forms.py
tuskar_ui/test/__init__.py
tuskar_ui/test/helpers.py
tuskar_ui/test/api_tests/heat_tests.py
tuskar_ui/test/api_tests/__init__.py
tuskar_ui/test/api_tests/tuskar_tests.py
tuskar_ui/test/api_tests/node_tests.py
tuskar_ui/test/test_data/flavor_data.py
tuskar_ui/test/test_data/tuskar_data.py
tuskar_ui/test/test_data/keystone_data.py
tuskar_ui/test/test_data/exceptions.py
tuskar_ui/test/test_data/node_data.py
tuskar_ui/test/test_data/__init__.py
tuskar_ui/test/test_data/utils.py
tuskar_ui/test/test_data/heat_data.py
tuskar_ui/api/tuskar.py
tuskar_ui/api/__init__.py
tuskar_ui/api/heat.py
tuskar_ui/api/node.py
tuskar_ui/api/flavor.py
tuskar_ui/infrastructure/__init__.py
tuskar_ui/infrastructure/dashboard.py
tuskar_ui/infrastructure/views.py
tuskar_ui/infrastructure/roles/urls.py
tuskar_ui/infrastructure/roles/__init__.py
tuskar_ui/infrastructure/roles/workflows.py
tuskar_ui/infrastructure/roles/panel.py
tuskar_ui/infrastructure/roles/tables.py
tuskar_ui/infrastructure/roles/tests.py
tuskar_ui/infrastructure/roles/views.py
tuskar_ui/infrastructure/roles/templates/roles/detail.html
tuskar_ui/infrastructure/roles/templates/roles/info.html
tuskar_ui/infrastructure/roles/templates/roles/config.html
tuskar_ui/infrastructure/roles/templates/roles/index.html
tuskar_ui/infrastructure/templates/formset_table/_row.html
tuskar_ui/infrastructure/templates/formset_table/menu_formset.html
tuskar_ui/infrastructure/templates/formset_table/_table.html
tuskar_ui/infrastructure/templates/infrastructure/_performance_chart.html
